{
  "run_time": "2026-05-14 10:20:16",
  "story_count": 11,
  "stories": [
    {
      "link": "https://apple.news/AczRk_myfR-yK35Ph58_xNQ",
      "rank": 1,
      "section": "top",
      "run_time": "2026-05-14 10:20:16",
      "pub_time": "",
      "publication": "The Wall Street Journal",
      "author": "",
      "headline": "Xi’s Taiwan warning to Trump highlights tensions in Beijing summit",
      "article_headline": "Xi’s Taiwan Warning to Trump Highlights Tensions in Beijing Summit"
    },
    {
      "link": "https://apple.news/As-33IxMgQD2SXVU12mXm3w",
      "rank": 2,
      "section": "top",
      "run_time": "2026-05-14 10:20:16",
      "pub_time": "2026-05-14 09:54:46",
      "publication": "The Associated Press",
      "author": "",
      "headline": "Tensions flare up over Strait of Hormuz as ship is reported seized and heading toward Iran",
      "article_headline": "Tensions flare up over Strait of Hormuz as ship is reported seized and heading toward Iran"
    },
    {
      "link": "https://apple.news/ApC-NOoxzSXuiwnQY68mCFQ",
      "rank": 3,
      "section": "top",
      "run_time": "2026-05-14 10:20:16",
      "pub_time": "2026-05-14 09:55:13",
      "publication": "USA TODAY",
      "author": "",
      "headline": "New El Niño forecast warns of a powerful shift amid hurricane season",
      "article_headline": "New El Niño forecast warns of a powerful shift amid hurricane season"
    },
    {
      "link": "https://apple.news/As-33IxMgQD2SXVU12mXm3w",
      "rank": 4,
      "section": "top",
      "run_time": "2026-05-14 10:20:16",
      "pub_time": "2026-05-14 09:54:45",
      "publication": "The Associated Press",
      "author": "",
      "headline": "Tensions flare up over Strait of Hormuz as ship is reported seized and heading toward Iran",
      "article_headline": "Tensions flare up over Strait of Hormuz as ship is reported seized and heading toward Iran"
    },
    {
      "link": "https://apple.news/ApC-NOoxzSXuiwnQY68mCFQ",
      "rank": 5,
      "section": "top",
      "run_time": "2026-05-14 10:20:16",
      "pub_time": "2026-05-14 09:55:13",
      "publication": "USA TODAY",
      "author": "",
      "headline": "New El Niño forecast warns of a powerful shift amid hurricane season",
      "article_headline": "New El Niño forecast warns of a powerful shift amid hurricane season"
    },
    {
      "link": "https://apple.news/AvwNTPTjRRaqnXN2bJ0Xm7w",
      "rank": 6,
      "section": "top",
      "run_time": "2026-05-14 10:20:16",
      "pub_time": "2026-05-14 09:54:40",
      "publication": "CNBC",
      "author": "Annika Kim Constantino",
      "headline": "Hantavirus isn’t another COVID, but experts say it’s testing U.S. readiness",
      "article_headline": "Hantavirus isn’t another COVID, but experts say it’s testing U.S. readiness"
    },
    {
      "link": "https://apple.news/AvwNTPTjRRaqnXN2bJ0Xm7w",
      "rank": 7,
      "section": "top",
      "run_time": "2026-05-14 10:20:16",
      "pub_time": "2026-05-14 09:54:13",
      "publication": "CNBC",
      "author": "Annika Kim Constantino",
      "headline": "Hantavirus isn’t another COVID, but experts say it’s testing U.S. readiness",
      "article_headline": "Hantavirus isn’t another COVID, but experts say it’s testing U.S. readiness"
    },
    {
      "link": "https://apple.news/A-ux0wJSWRgSeUVkBd-oWXQ",
      "rank": 1,
      "section": "trending",
      "run_time": "2026-05-14 10:20:16",
      "pub_time": "2026-05-13 23:24:22",
      "publication": "BuzzFeed",
      "author": "Julie Kendrick",
      "headline": "\"It Isn’t Worth The Risk Of Getting Salmonella\": 3 Foods Food Safety Lawyers Are Recommending You Never Eat",
      "article_headline": "\"It Isn’t Worth The Risk Of Getting Salmonella\": 3 Foods Food Safety Lawyers Are Recommending You Never Eat"
    },
    {
      "link": "https://apple.news/AD-c8w99hTsul6so4L7HjQw",
      "rank": 2,
      "section": "trending",
      "run_time": "2026-05-14 10:20:16",
      "pub_time": "2026-05-14 06:24:49",
      "publication": "Chicago Sun-Times",
      "author": "",
      "headline": "Dear Abby: Three's a crowd in family's housing arrangement",
      "article_headline": "Dear Abby: Three's a crowd in family's housing arrangement"
    },
    {
      "link": "",
      "rank": 3,
      "section": "trending",
      "run_time": "2026-05-14 10:20:16",
      "pub_time": "2026-05-14 09:43:16",
      "publication": "",
      "author": "Jason Sobel",
      "headline": "PGA Championship 2026 Big Board: Who can stop Scottie Scheffler’s repeat bid?",
      "article_headline": "",
      "link_status": "P"
    },
    {
      "link": "",
      "rank": 4,
      "section": "trending",
      "run_time": "2026-05-14 10:20:16",
      "pub_time": "2026-05-14 09:42:22",
      "publication": "",
      "author": "Jason Sobel",
      "headline": "PGA Championship 2026 Big Board: Who can stop Scottie Scheffler’s repeat bid?",
      "article_headline": "",
      "link_status": "P"
    }
  ]
}