{
  "run_time": "2026-05-02 13:20:16",
  "story_count": 7,
  "stories": [
    {
      "link": "https://apple.news/ASmY7z6hdSsmOXXd415nmIA",
      "rank": 1,
      "section": "top",
      "run_time": "2026-05-02 13:20:16",
      "pub_time": "",
      "publication": "NBC News",
      "author": "",
      "headline": "Spirit Airlines is shutting down, effective immediately",
      "article_headline": "Spirit Airlines is shutting down, effective immediately"
    },
    {
      "link": "https://apple.news/AEzVRqOi6SPmuillg86BVqA",
      "rank": 2,
      "section": "top",
      "run_time": "2026-05-02 13:20:16",
      "pub_time": "",
      "publication": "The Associated Press",
      "author": "",
      "headline": "A federal court blocked a widely used abortion pill from distribution by mail. Here’s what to know.",
      "article_headline": "A federal court blocked a widely used abortion pill from distribution by mail. Here’s what to know."
    },
    {
      "link": "https://apple.news/Aptq2TlP6QY-Qe141O5vn6Q",
      "rank": 3,
      "section": "top",
      "run_time": "2026-05-02 13:20:16",
      "pub_time": "2026-05-02 11:21:18",
      "publication": "The Guardian",
      "author": "Deborah Cole",
      "headline": "The German town rocked by Trump’s plan to withdraw U.S. troops",
      "article_headline": "The German town rocked by Trump’s plan to withdraw U.S. troops"
    },
    {
      "link": "",
      "rank": "plus",
      "section": "top",
      "run_time": "2026-05-02 13:20:16",
      "pub_time": "2026-05-02 11:21:46",
      "publication": "The Washington Post",
      "author": "Julian Mark and Eva Dou",
      "headline": "Tortured in China, they want to sue Cisco. The Supreme Court may say no.",
      "article_headline": "",
      "link_status": "P"
    },
    {
      "link": "https://apple.news/AcQKNWBk7RMiIpJHkYpZDqQ?route=aHR0cHM6Ly9hcHBsZS5uZXdzL1RVOXh4R1dSV1NQU011R0xGMTR0VF9BI25mZl9paWQ%3D",
      "rank": 4,
      "section": "top",
      "run_time": "2026-05-02 13:20:16",
      "pub_time": "",
      "publication": "Apple News Spotlight",
      "author": "",
      "headline": "Climate, Whales are losing their ice refuge. Plus, the energy goldmine buried beneath the U.S.",
      "article_headline": ""
    },
    {
      "link": "",
      "rank": "plus",
      "section": "top",
      "run_time": "2026-05-02 13:20:16",
      "pub_time": "2026-05-02 11:22:18",
      "publication": "The Wall Street Journal",
      "author": "E.B. Solomont",
      "headline": "Will a Los Angeles megamansion become America’s first $400 million home?",
      "article_headline": "",
      "link_status": "P"
    },
    {
      "link": "https://apple.news/AGBfD-tiASgyrwZftLVK3zA",
      "rank": 5,
      "section": "top",
      "run_time": "2026-05-02 13:20:16",
      "pub_time": "",
      "publication": "Block Club Chicago",
      "author": "",
      "headline": "Local News, Chicago, Thousands take to Chicago streets for May Day demonstrations",
      "article_headline": "Thousands take to Chicago streets for May Day demonstrations"
    }
  ]
}