{
  "run_time": "2026-04-29 07:20:16",
  "story_count": 14,
  "stories": [
    {
      "link": "https://apple.news/AZCKbtKIoQgOQnhcgUDb4Ww",
      "rank": 1,
      "section": "top",
      "run_time": "2026-04-29 07:20:16",
      "pub_time": "2026-04-29 06:28:18",
      "publication": "The Wall Street Journal",
      "author": "Alexander Ward, Laurence Norman, and Summer Said",
      "headline": "Trump tells aides to prepare for extended blockade of Iran",
      "article_headline": "Trump tells aides to prepare for extended blockade of Iran"
    },
    {
      "link": "",
      "rank": "plus",
      "section": "top",
      "run_time": "2026-04-29 07:20:16",
      "pub_time": "2026-04-29 06:28:45",
      "publication": "The Washington Post",
      "author": "Jonathan O'Connell, Sarah Blaskey, Joyce Lee, Samuel Oakford, and Alex Horton",
      "headline": "Video shows moment Secret Service officer fired at correspondents’ dinner suspect",
      "article_headline": "",
      "link_status": "P"
    },
    {
      "link": "https://apple.news/AecjleEuWSy-GtXm6f6-nfA",
      "rank": 2,
      "section": "top",
      "run_time": "2026-04-29 07:20:16",
      "pub_time": "",
      "publication": "POLITICO",
      "author": "",
      "headline": "DeSantis’s Florida redistricting map advances, but draws GOP no votes and legal scrutiny",
      "article_headline": "DeSantis’s Florida redistricting map advances, but draws GOP no votes and legal scrutiny"
    },
    {
      "link": "https://apple.news/AZim8jsdBQVC5m3yBHvtr8g",
      "rank": 3,
      "section": "top",
      "run_time": "2026-04-29 07:20:16",
      "pub_time": "2026-04-29 06:29:17",
      "publication": "The Associated Press",
      "author": "",
      "headline": "King Charles III and Queen Camilla visiting 9/11 Memorial and other New York landmarks",
      "article_headline": "King Charles III and Queen Camilla visiting 9/11 Memorial and other New York landmarks"
    },
    {
      "link": "https://apple.news/AZim8jsdBQVC5m3yBHvtr8g",
      "rank": 4,
      "section": "top",
      "run_time": "2026-04-29 07:20:16",
      "pub_time": "2026-04-29 06:28:50",
      "publication": "The Associated Press",
      "author": "",
      "headline": "King Charles III and Queen Camilla visiting 9/11 Memorial and other New York landmarks",
      "article_headline": "King Charles III and Queen Camilla visiting 9/11 Memorial and other New York landmarks"
    },
    {
      "link": "",
      "rank": "plus",
      "section": "top",
      "run_time": "2026-04-29 07:20:16",
      "pub_time": "2026-04-29 06:29:17",
      "publication": "National Geographic",
      "author": "Daryl Austin",
      "headline": "How science is finally making real progress in treating allergies — and what it means for you",
      "article_headline": "",
      "link_status": "P"
    },
    {
      "link": "",
      "rank": "plus",
      "section": "top",
      "run_time": "2026-04-29 07:20:16",
      "pub_time": "",
      "publication": "The Wall Street Journal",
      "author": "",
      "headline": "The Sphere looked like a disaster. It’s become a huge hit instead.",
      "article_headline": "",
      "link_status": "P"
    },
    {
      "link": "https://apple.news/AIQ-DreyDRU2xTKRbG1CoyA",
      "rank": 1,
      "section": "trending",
      "run_time": "2026-04-29 07:20:16",
      "pub_time": "2026-04-28 12:22:22",
      "publication": "Good Housekeeping",
      "author": "Kate Franke",
      "headline": "Experts Reveal the Right Time to Shower, and It May Not Be When You Think",
      "article_headline": "Experts Reveal the Right Time to Shower, and It May Not Be When You Think"
    },
    {
      "link": "https://apple.news/AOsPh8I0hSZG1az1hM1bUxQ",
      "rank": 2,
      "section": "trending",
      "run_time": "2026-04-29 07:20:16",
      "pub_time": "2026-04-28 19:22:55",
      "publication": "USA TODAY",
      "author": "",
      "headline": "Alligator at large after killing cow, forcing Florida park to close",
      "article_headline": "Alligator at large after killing cow, forcing Florida park to close"
    },
    {
      "link": "",
      "rank": 3,
      "section": "trending",
      "run_time": "2026-04-29 07:20:16",
      "pub_time": "2026-04-28 07:23:22",
      "publication": "",
      "author": "Carrie Myers, M.S.",
      "headline": "This Popular Supplement May Help Feed Cancer Cells, New Study Says",
      "article_headline": "",
      "link_status": "P"
    },
    {
      "link": "https://apple.news/Ak9Q3PzgXTAyX2hOZQGuK7Q",
      "rank": 4,
      "section": "trending",
      "run_time": "2026-04-29 07:20:16",
      "pub_time": "2026-04-29 06:23:22",
      "publication": "Reuters",
      "author": "Johan Ahlander and Tom Little",
      "headline": "Ukraine war flips Sweden’s Hagglunds fortunes from layoffs to billions",
      "article_headline": "Ukraine war flips Sweden’s Hagglunds fortunes from layoffs to billions"
    },
    {
      "link": "",
      "rank": 1,
      "section": "reader_favorites",
      "run_time": "2026-04-29 07:20:16",
      "pub_time": "",
      "publication": "Consumer Reports",
      "author": "",
      "headline": "Eight cars you should never buy, according to experts",
      "article_headline": "",
      "link_status": "P"
    },
    {
      "link": "",
      "rank": 2,
      "section": "reader_favorites",
      "run_time": "2026-04-29 07:20:16",
      "pub_time": "",
      "publication": "National Geographic",
      "author": "",
      "headline": "Can exercise offset the health risks of alcohol? , Hannah Singleton",
      "article_headline": "",
      "link_status": "P"
    },
    {
      "link": "",
      "rank": 3,
      "section": "reader_favorites",
      "run_time": "2026-04-29 07:20:16",
      "pub_time": "",
      "publication": "Slate",
      "author": "",
      "headline": "Inside the stunning downfall of Wendy’s , Adam Chandler",
      "article_headline": "",
      "link_status": "P"
    }
  ]
}