{
  "run_time": "2026-05-15 08:20:16",
  "story_count": 11,
  "stories": [
    {
      "link": "https://apple.news/AzG7qEqTxQUODKQacRDBdwQ",
      "rank": 1,
      "section": "top",
      "run_time": "2026-05-15 08:20:16",
      "pub_time": "",
      "publication": "The Associated Press",
      "author": "",
      "headline": "Trump and Xi wrap talks, citing progress stabilizing U.S.-China relations. But differences persist.",
      "article_headline": "Trump and Xi wrap talks, citing progress stabilizing U.S.-China relations. But differences persist."
    },
    {
      "link": "https://apple.news/ASud_sTFIQYaGjUF2vPXoig",
      "rank": 2,
      "section": "top",
      "run_time": "2026-05-15 08:20:16",
      "pub_time": "",
      "publication": "The Hill",
      "author": "",
      "headline": "Jerome Powell ends term as Federal Reserve chief clouded by Trump tumult",
      "article_headline": "Jerome Powell ends term as Federal Reserve chief clouded by Trump tumult"
    },
    {
      "link": "https://apple.news/Arew2cK8xSxaMkL7h8yQ2-Q",
      "rank": 3,
      "section": "top",
      "run_time": "2026-05-15 08:20:16",
      "pub_time": "2026-05-15 07:59:18",
      "publication": "Reuters",
      "author": "Yurii Kovalenko and Olena Harmash",
      "headline": "Zelenskyy rages at Russia after strike on Kyiv apartment building kills 24",
      "article_headline": "Zelenskyy rages at Russia after strike on Kyiv apartment building kills 24"
    },
    {
      "link": "",
      "rank": "plus",
      "section": "top",
      "run_time": "2026-05-15 08:20:16",
      "pub_time": "2026-05-15 07:59:45",
      "publication": "BBC Sky at Night Magazine",
      "author": "Iain Todd",
      "headline": "Asteroid the size of a basketball court to skim past Earth, even closer than the Moon",
      "article_headline": "",
      "link_status": "P"
    },
    {
      "link": "",
      "rank": "plus",
      "section": "top",
      "run_time": "2026-05-15 08:20:16",
      "pub_time": "",
      "publication": "The Times of London",
      "author": "",
      "headline": "David Beckham joins ranks of sports billionaires after bet on Miami soccer team pays off",
      "article_headline": "",
      "link_status": "P"
    },
    {
      "link": "",
      "rank": "plus",
      "section": "top",
      "run_time": "2026-05-15 08:20:16",
      "pub_time": "2026-05-15 07:58:50",
      "publication": "The Wall Street Journal",
      "author": "Roshan Fernandez",
      "headline": "The only thing harder than getting into college is getting off the wait list",
      "article_headline": "",
      "link_status": "P"
    },
    {
      "link": "https://apple.news/AX67A0puXRiWl8Uol5q9AwQ",
      "rank": "audio",
      "section": "top",
      "run_time": "2026-05-15 08:20:16",
      "pub_time": "",
      "publication": "Apple News Today",
      "author": "",
      "headline": "Vessels attacked in the Strait of Hormuz as sailors grow desperate",
      "article_headline": ""
    },
    {
      "link": "https://apple.news/AcHAYX6A1S-qh_LsMSFPIOw",
      "rank": 1,
      "section": "trending",
      "run_time": "2026-05-15 08:20:16",
      "pub_time": "2026-05-14 21:22:53",
      "publication": "BuzzFeed",
      "author": "Julia Corrigan",
      "headline": "18 Things That Were “Normal” And “Affordable” In America 10 Years Ago That Now Feel Completely Out Of Reach",
      "article_headline": "18 Things That Were “Normal” And “Affordable” In America 10 Years Ago That Now Feel Completely Out Of Reach"
    },
    {
      "link": "https://apple.news/AXK1t4QVMT6Kja4QmO8t2YQ",
      "rank": 2,
      "section": "trending",
      "run_time": "2026-05-15 08:20:16",
      "pub_time": "2026-05-14 11:23:26",
      "publication": "Good Housekeeping",
      "author": "The Editors",
      "headline": "6 Foods Americans Love That Are Banned in Other Countries",
      "article_headline": "6 Foods Americans Love That Are Banned in Other Countries"
    },
    {
      "link": "",
      "rank": 3,
      "section": "trending",
      "run_time": "2026-05-15 08:20:16",
      "pub_time": "2026-05-14 08:23:53",
      "publication": "",
      "author": "Skyler Trepel",
      "headline": "'The Sopranos' Ending Explained: What Really Happened When the Screen Cut to Black",
      "article_headline": "",
      "link_status": "P"
    },
    {
      "link": "https://apple.news/Ak6smXpGRQN2DHXTf0QcrDw",
      "rank": 4,
      "section": "trending",
      "run_time": "2026-05-15 08:20:16",
      "pub_time": "2026-05-14 13:23:53",
      "publication": "Southern Living",
      "author": "Meghan Overdeep",
      "headline": "What Does The Air Recirculation Button Do? You Might Be Using It Wrong",
      "article_headline": "What Does The Air Recirculation Button Do? You Might Be Using It Wrong"
    }
  ]
}