{
  "run_time": "2026-05-13 23:20:16",
  "story_count": 11,
  "stories": [
    {
      "link": "https://apple.news/AvDUnE89zTt6lR7bDiSfWeA",
      "rank": 1,
      "section": "top",
      "run_time": "2026-05-13 23:20:16",
      "pub_time": "",
      "publication": "The Wall Street Journal",
      "author": "",
      "headline": "Trump meets Xi for China summit against backdrop of Iran war, LIVE",
      "article_headline": "Trump Meets Xi for China Summit Against Backdrop of Iran War"
    },
    {
      "link": "https://apple.news/AMZWdkflcR4mmTn4U2Xwa5Q",
      "rank": 2,
      "section": "top",
      "run_time": "2026-05-13 23:20:16",
      "pub_time": "",
      "publication": "The Associated Press",
      "author": "",
      "headline": "Denise Powell wins Democratic primary in Nebraska’s “blue dot” 2nd District",
      "article_headline": "Denise Powell wins Democratic primary in Nebraska’s ‘blue dot’ 2nd District"
    },
    {
      "link": "https://apple.news/ALIGUI_f2RQyY_HEqyOEAEQ",
      "rank": 3,
      "section": "top",
      "run_time": "2026-05-13 23:20:16",
      "pub_time": "2026-05-13 22:21:17",
      "publication": "POLITICO",
      "author": "Kyle Cheney",
      "headline": "10,000 rulings: The courts’ overwhelming rebuke of Trump’s ICE policies",
      "article_headline": "10,000 rulings: The courts’ overwhelming rebuke of Trump’s ICE policies"
    },
    {
      "link": "https://apple.news/AfDx5D21YQv6DVE84DP7UVQ",
      "rank": 4,
      "section": "top",
      "run_time": "2026-05-13 23:20:16",
      "pub_time": "2026-05-13 22:21:45",
      "publication": "CBS News",
      "author": "Jordan Freiman",
      "headline": "Body of second U.S. soldier who went missing in Morocco recovered",
      "article_headline": "Body of second U.S. soldier who went missing in Morocco recovered"
    },
    {
      "link": "https://apple.news/AFc3Ywv26SfKsO9My-HrwOg",
      "rank": 5,
      "section": "top",
      "run_time": "2026-05-13 23:20:16",
      "pub_time": "",
      "publication": "Inside Climate News",
      "author": "",
      "headline": "An unusual heat wave strains the world’s most populous country",
      "article_headline": "An unusual heat wave strains the world’s most populous country"
    },
    {
      "link": "",
      "rank": "plus",
      "section": "top",
      "run_time": "2026-05-13 23:20:16",
      "pub_time": "2026-05-13 22:22:45",
      "publication": "The New Yorker",
      "author": "Akash Kapur",
      "headline": "A scientist’s close call with hantavirus aboard the M.V. Hondius cruise",
      "article_headline": "",
      "link_status": "P"
    },
    {
      "link": "https://apple.news/AE9OtGuEjRbqsT3td37HVPA",
      "rank": 6,
      "section": "top",
      "run_time": "2026-05-13 23:20:16",
      "pub_time": "2026-05-13 16:23:00",
      "publication": "BuzzFeed",
      "author": "Matt Stopera",
      "headline": "Rod Stewart Just Gave Donald Trump A New Nickname And It’s Truly The Most British Insult Ever",
      "article_headline": "Rod Stewart Just Gave Donald Trump A New Nickname And It’s Truly The Most British Insult Ever"
    },
    {
      "link": "",
      "rank": 1,
      "section": "trending",
      "run_time": "2026-05-13 23:20:16",
      "pub_time": "2026-05-13 14:23:43",
      "publication": "",
      "author": "Catherine Santino",
      "headline": "Man Tears Up After Learning Shocking Value of Handbag He Thrifted for $1.50",
      "article_headline": ""
    },
    {
      "link": "",
      "rank": 2,
      "section": "trending",
      "run_time": "2026-05-13 23:20:16",
      "pub_time": "2026-05-13 11:24:00",
      "publication": "",
      "author": "Katherine Bindley",
      "headline": "The Tech Jobs That Are Safe From AI",
      "article_headline": "",
      "link_status": "P"
    },
    {
      "link": "https://apple.news/AITIl4RrDQYugapwBblOqow",
      "rank": 3,
      "section": "trending",
      "run_time": "2026-05-13 23:20:16",
      "pub_time": "2026-05-13 19:24:00",
      "publication": "Travel + Leisure",
      "author": "Lydia Mansel",
      "headline": "10 Best Places to Buy a Lake House in the U.S. Right Now, According to Real Estate Experts",
      "article_headline": "10 Best Places to Buy a Lake House in the U.S. Right Now, According to Real Estate Experts"
    },
    {
      "link": "https://apple.news/AOAUBaYtZRqetQ8da3AeBEQ",
      "rank": 4,
      "section": "trending",
      "run_time": "2026-05-13 23:20:16",
      "pub_time": "2026-05-13 13:24:27",
      "publication": "Autoblog",
      "author": "John Tallodi",
      "headline": "The Least Reliable Midsize SUVs You Can Buy In 2026",
      "article_headline": "The Least Reliable Midsize SUVs You Can Buy In 2026"
    }
  ]
}